{
  "id": "79a04e82-71a0-4e3a-9d10-625ab5e90414",
  "prevId": "00000000-0000-0000-0000-000000000000",
  "version": "7",
  "dialect": "postgresql",
  "tables": {
    "public.courses": {
      "name": "courses",
      "schema": "",
      "columns": {
        "id": {
          "name": "id",
          "type": "uuid",
          "primaryKey": true,
          "notNull": true,
          "default": "gen_random_uuid()"
        },
        "title": {
          "name": "title",
          "type": "text",
          "primaryKey": false,
          "notNull": true
        },
        "description": {
          "name": "description",
          "type": "text",
          "primaryKey": false,
          "notNull": true
        },
        "user_id": {
          "name": "user_id",
          "type": "uuid",
          "primaryKey": false,
          "notNull": true
        },
        "created_at": {
          "name": "created_at",
          "type": "timestamp",
          "primaryKey": false,
          "notNull": false,
          "default": "now()"
        },
        "updated_at": {
          "name": "updated_at",
          "type": "timestamp",
          "primaryKey": false,
          "notNull": false,
          "default": "now()"
        }
      },
      "indexes": {},
      "foreignKeys": {
        "courses_user_id_users_id_fk": {
          "name": "courses_user_id_users_id_fk",
          "tableFrom": "courses",
          "tableTo": "users",
          "columnsFrom": [
            "user_id"
          ],
          "columnsTo": [
            "id"
          ],
          "onDelete": "cascade",
          "onUpdate": "no action"
        }
      },
      "compositePrimaryKeys": {},
      "uniqueConstraints": {},
      "policies": {},
      "checkConstraints": {},
      "isRLSEnabled": false
    },
    "public.semesters": {
      "name": "semesters",
      "schema": "",
      "columns": {
        "id": {
          "name": "id",
          "type": "uuid",
          "primaryKey": true,
          "notNull": true,
          "default": "gen_random_uuid()"
        },
        "title": {
          "name": "title",
          "type": "text",
          "primaryKey": false,
          "notNull": true
        },
        "course_id": {
          "name": "course_id",
          "type": "uuid",
          "primaryKey": false,
          "notNull": true
        },
        "created_at": {
          "name": "created_at",
          "type": "timestamp",
          "primaryKey": false,
          "notNull": false,
          "default": "now()"
        },
        "updated_at": {
          "name": "updated_at",
          "type": "timestamp",
          "primaryKey": false,
          "notNull": false,
          "default": "now()"
        }
      },
      "indexes": {},
      "foreignKeys": {
        "semesters_course_id_courses_id_fk": {
          "name": "semesters_course_id_courses_id_fk",
          "tableFrom": "semesters",
          "tableTo": "courses",
          "columnsFrom": [
            "course_id"
          ],
          "columnsTo": [
            "id"
          ],
          "onDelete": "cascade",
          "onUpdate": "cascade"
        }
      },
      "compositePrimaryKeys": {},
      "uniqueConstraints": {},
      "policies": {},
      "checkConstraints": {},
      "isRLSEnabled": false
    },
    "public.users": {
      "name": "users",
      "schema": "",
      "columns": {
        "id": {
          "name": "id",
          "type": "uuid",
          "primaryKey": true,
          "notNull": true,
          "default": "gen_random_uuid()"
        },
        "name": {
          "name": "name",
          "type": "text",
          "primaryKey": false,
          "notNull": true
        },
        "email": {
          "name": "email",
          "type": "text",
          "primaryKey": false,
          "notNull": true
        },
        "password": {
          "name": "password",
          "type": "text",
          "primaryKey": false,
          "notNull": true
        },
        "created_at": {
          "name": "created_at",
          "type": "timestamp",
          "primaryKey": false,
          "notNull": false,
          "default": "now()"
        },
        "updated_at": {
          "name": "updated_at",
          "type": "timestamp",
          "primaryKey": false,
          "notNull": false,
          "default": "now()"
        }
      },
      "indexes": {},
      "foreignKeys": {},
      "compositePrimaryKeys": {},
      "uniqueConstraints": {
        "users_email_unique": {
          "name": "users_email_unique",
          "nullsNotDistinct": false,
          "columns": [
            "email"
          ]
        }
      },
      "policies": {},
      "checkConstraints": {},
      "isRLSEnabled": false
    }
  },
  "enums": {},
  "schemas": {},
  "sequences": {},
  "roles": {},
  "policies": {},
  "views": {},
  "_meta": {
    "columns": {},
    "schemas": {},
    "tables": {}
  }
}